Mips.v
module MipsCPU(CLK, rst, PCIn,PCNext,Instruction,write_reg,ReadData1, ReadData2,ALUControl,Zero,read_data,write_data_reg);	
	
	input CLK,rst;
	output wire Zero;
      output wire [4:0] write_reg;
	output wire [3:0] ALUControl;
	output wire [31:0] PCNext,PCIn,Instruction,ReadData1, ReadData2,write_data_reg,read_data;
	
	wire reg_dst, reg_write, mem_toreg,ALUCtl, mem_read, mem_write, branch,branch_ne, j,branch_Zero_and,bne_nZero_and,branching;
	wire [3:0] alu_op;
	wire [31:0] add_alu_out,pc_out_alu,alu_out,shift_out,alu_b,extend32;

	//Orginal Unit
	prgram_counter PC(CLK,rst,PCIn,PCNext);
	intruction_memory IM(CLK,PCIn,Instruction);
	reg_file RF(CLK,reg_write,Instruction[25:21],Instruction[20:16],write_reg,write_data_reg,ReadData1,ReadData2);
	data_memory  DM(CLK,alu_out,mem_write,mem_read,ReadData2,read_data);

	//Control Unit
	control_unit CONTROL(Instruction[31:26],reg_dst,reg_write,alu_src,mem_toreg,mem_read,mem_write,branch,branch_ne,j,alu_op);
	alu_control_unit ALUCTRL(alu_op,Instruction[5:0],ALUControl);

	//Contivites Unit
	mux_before_regfile BEF_RF(Instruction[20:16],Instruction[15:11],reg_dst,write_reg);
	mux_affter_regfile AFT_RF(alu_src,ReadData2,extend32,alu_b);
	sign_extend SE16TO32(Instruction[15:0],extend32);
	shift_left_2bit ADD_ALU_B(extend32,shift_out);	
	alu ADDRESS(ALUControl,ReadData1,alu_b,alu_out,Zero);
	pc_adder PCADDER(PCNext,shift_out,add_alu_out);	
	
	and(branch_Zero_and,branch,Zero);
	and(bne_Zero_and,branch_ne,~Zero);
	or(branching,branch_Zero_and,bne_Zero_and);

	mux_after_alu mux4_0(PCNext,add_alu_out,branching,pc_out_alu);
	mux_affter_memory mu3_0(read_data,alu_out,mem_toreg,write_data_reg);
	JCall JUPM(pc_out_alu,ReadData1,j,PCIn);

endmodule

module alu (ALUControl, A, B, alu_out, Zero);
	input [3:0] ALUControl;
	input [31:0] A,B;
	output Zero;
	output reg [31:0] alu_out;
   
	assign Zero   = (alu_out == 0);
	// assign n_Zero = (alu_out != 0);

	always @(ALUControl, A, B) begin
		case (ALUControl)
			0: alu_out = A & B;
			1: alu_out = A | B;
			2: alu_out = A + B;
			3: alu_out = A - B;
			
			default: alu_out = 0;
		endcase
	end
endmodule


module alu_control_unit (alu_op, func, ALUControl);
  
	input      [3:0]  alu_op;
	input      [5:0]  func;
	output reg [3:0]  ALUControl;
	wire       [5:0]  AND   = 6'b100100, OR  = 6'b100101, ADD  = 6'b100000, SUB = 6'b100010; 


	always @(alu_op, func) begin
	if      (alu_op == 0) begin ALUControl <= 2;      end   //LW and SW use add
	else if (alu_op == 1) begin ALUControl <= 3;      end   // branch use subtract
	else if (alu_op == 2) begin ALUControl <= 2;      end   //add
	else if (alu_op == 3) begin ALUControl <= 3;      end   //sub
	else if (alu_op == 4) begin ALUControl <= 0;      end   //and
	else if (alu_op == 5) begin ALUControl <= 1;      end   //or
	else
		case(func)
			AND: 		ALUControl  <= 0; 	
			OR : 		ALUControl  <= 1; 	
			ADD: 		ALUControl  <= 2; 
			SUB: 		ALUControl  <= 3; 
		endcase
	end
endmodule


module control_unit(opcode,reg_dst,reg_write, alu_src,mem_toreg, mem_read, mem_write,branch,branch_ne,j,alu_op);
	
	input [5:0] opcode;
	output reg reg_dst,reg_write, alu_src,j,mem_toreg, mem_read, mem_write,branch,branch_ne;
	output reg [3:0] alu_op;
 
   wire [5:0] LW = 6'b100011/*35*/, SW  = 6'b101011/*43*/, ADDI = 6'b001000/*8*/,
              SUBI  = 6'b100111/*42*/, ANDI  = 6'b101111/*50*/, ORI  = 6'b110010/*8*/,
	 	  BEQ   = 6'b000100/*4*/, J = 6'b000010/*2*/,RTYPE = 6'b000000/*0*/;
				  
	
	always @(*) begin
		//reset...
		reg_dst 		<= 0;
		alu_src 		<= 0;
		mem_toreg	<= 0;
		reg_write	<= 0;
		mem_read		<= 0;
		mem_write	<= 0;
		branch		<= 0;
		j		      <= 0;

		//select oprand
		case(opcode)	
			LW: begin
				alu_src 		<= 1;
				reg_write	<= 1;
				mem_read		<= 1;
				mem_write	<= 1;
				alu_op		<= 4'b0000;/*0*/
			end
			SW: begin
				alu_src 		<= 1;
				mem_write	<= 1;
				alu_op		<= 4'b0000;/*0*/
			end
			BEQ: begin
				branch		<= 1;
				alu_op		<= 4'b0001;/*1*/
			end
			ADDI: begin
				alu_src 		<= 1;
				reg_write	<= 1;
				alu_op		<= 4'b0010;/*2*/
			end
			SUBI: begin
				alu_src 		<= 1;
				reg_write	<= 1;
				alu_op		<= 4'b0011;/*3*/
			end
			ANDI: begin
				alu_src 		<= 1;
				reg_write	<= 1;
				alu_op		<= 4'b0101;/*5*/
			end
			ORI: begin
				alu_src 		<= 1;
				reg_write	<= 1;
				alu_op		<= 4'b0111;/*7*/
			end
			J: begin
				j              <= 1;
				// alu_op			<= 4'bxxxx;
			end
			RTYPE: begin
				reg_dst 		<= 1;
				reg_write		<= 1;
				alu_op		<= 4'b1111;
			end
		endcase
	end
endmodule


module  data_memory (CLK, addr,mem_write, mem_read,write_data,read_data);

	input wire CLK,mem_write, mem_read;
	input wire [31:0] addr,write_data;
	output reg [31:0] read_data;

   reg [31:0] Mem[0:255];

   integer i;

   initial begin
		read_data <= 0;
		for (i = 0; i < 256; i = i + 1) begin
			Mem[i] = i;
		end
   end

   always @(posedge CLK) begin
		if (mem_write == 1) begin
			Mem[addr] <= write_data;
		end
		if (mem_read == 1) begin
			read_data <= Mem[addr];
		end
   end

endmodule

module intruction_memory(CLK, address, Instruction);

	input CLK;
	input [31:0] address;
	output reg [31:0]	Instruction;
	reg [31:0] IMEM [0:127];
	
	initial begin
		//r-tpe  -> rd,rs,rt
		IMEM[1]= 32'b000000_00100_00001_00100_00000_100000;//add $mul,$mul,$a;
            IMEM[2] = 32'b10001100001001010000000000000011;// lw $5, 3($1 = 4)
		IMEM[3]= 32'b000000_00101_00011_00100_00000_101011;//add 
		IMEM[4]= 32'b000100_00111_00111_0000000000000111; //beq $t0,$0,EXIT [jump 3 => line 10]
	end

	always @( posedge CLK) Instruction <= IMEM[address[31:2]];
endmodule


module JCall(pc_out_alu,ReadData1,j,PCIn);
	input [31:0] pc_out_alu, ReadData1;
	input j;	
	
	output reg [31:0] PCIn;
	
	always @(*) begin
		if   (j) begin PCIn <= ReadData1; end
		else     begin PCIn <= pc_out_alu;     end
	end
endmodule


module mux_after_alu (PCNext, add_alu_out, branch_Zero_and, PCIn);
	input [31:0] PCNext, add_alu_out;
	input branch_Zero_and;	
	
	output reg [31:0] PCIn;
	
	initial PCIn <= 0;

	always @(*) begin
		if(branch_Zero_and) begin PCIn <= add_alu_out; end 
		else begin  PCIn <= PCNext ; end
	end
endmodule


module mux_affter_memory (read_data, alu_out, mem_toreg, write_data_reg);

	input [31:0] read_data, alu_out;
	input mem_toreg;	
	
	output reg [31:0] write_data_reg;
	
	always @(*) begin
		case (mem_toreg)
			0: write_data_reg <= alu_out ;
			1: write_data_reg <= read_data;
		endcase
	end
endmodule


module mux_affter_regfile (alu_src, ReadData2, extend32, alu_b);

	input alu_src;
	input [31:0] ReadData2,extend32;	
	
	output reg [31:0] alu_b;
	
	always @(alu_src, ReadData2, extend32) begin
		case (alu_src)
			0: alu_b <= ReadData2 ;
			1: alu_b <= extend32;
		endcase
	end
endmodule

module mux_before_regfile(rt, rd, reg_dst, write_reg);

	input [20:16] rt;
	input [15:11] rd;
	input reg_dst;
	
	output reg [4:0] write_reg;

	always @ (reg_dst, rt, rd) begin
		if(reg_dst == 1) begin  write_reg <= rd; end
		else  begin write_reg <= rt; end
	end

endmodule

module pc_adder(PCNext, shift_out, add_alu_out);

	input [31:0] PCNext;
	input [31:0] shift_out;
	
	output reg [31:0] add_alu_out;

	always @(*) begin
		add_alu_out <= PCNext + shift_out;
	end
endmodule

module prgram_counter(CLK, rst, PCIn, PCNext);

	input CLK, rst;
	input [31:0] PCIn;
	
	output reg [31:0] PCNext;
	
	always @(posedge CLK) begin
		if (rst == 1) 
		    PCNext <= 0;
		else 
		    PCNext <= PCIn + 4; 
	end
	
endmodule

module reg_file(CLK, reg_write, read_reg1, read_reg2, write_reg, write_data, ReadData1, ReadData2);

	input CLK;
	input reg_write;
	input [4:0] read_reg1, read_reg2, write_reg;
	input [31:0] write_data;
		
	output [31:0] ReadData1, ReadData2;
	
	reg [31:0] reg_mem [0:31];

	initial begin
		reg_mem[0] <= 0;
		reg_mem[1] <= 4;
		reg_mem[2] <= 8;
            reg_mem[3] <= 12; 
            reg_mem[4] <= 16;
            reg_mem[5] <= 16;
            reg_mem[6] <= 16;
            reg_mem[7] <= 16;
            reg_mem[8] <= 60;
            reg_mem[9] <= 13;
            reg_mem[10] <= 13;
            reg_mem[14] <= 1;
		reg_mem[31] <=16;//lable Exit
	end
	
	assign ReadData1 = reg_mem[read_reg1];
	assign ReadData2 = reg_mem[read_reg2];
	
	always @(posedge CLK) begin
		if (reg_write == 1)
			reg_mem[write_reg] = write_data;
	end	
endmodule


module shift_left_2bit (ShiftIn, shift_out);

	input [31:0] ShiftIn;
	output reg [31:0] shift_out;
	
	always @(ShiftIn) begin
		shift_out = ShiftIn << 2;
	end 
	
endmodule

module sign_extend (in16, out32);

	input [15:0] in16;
	output reg [31:0] out32;

	always @(in16) out32[31:0] <= in16[15:0];
	
endmodule

MipsTest.v
`include "Mips.v"
`timescale 1ns/1ns

module tb_mips();
  	reg CLK,rst;
   integer i;
	wire Zero;
   wire [4:0]  write_reg;
   wire [3:0]  ALUControl;
	wire [31:0] PCNext,PCIn,Instruction,ReadData1,ReadData2,write_data_reg,read_data;
   

   initial
        begin
        rst=1;
        CLK=0;
        CLK=1;
        #50;
        rst=0;
        for(i=0;i<20;i=i+1)
        begin
            CLK=~CLK;
            #50;
        end
   end
	   
	MipsCPU mcpu(CLK, rst, PCIn,PCNext,Instruction,write_reg,ReadData1, ReadData2,ALUControl,Zero,read_data,write_data_reg);

      initial begin

        $dumpfile("Mips.vcd");
        $dumpvars(0,tb_mips); 

      end

endmodule

Mips.vcd
$date
	Thu Jun 16 19:17:11 2022
$end
$version
	Icarus Verilog
$end
$timescale
	1ns
$end
$scope module tb_mips $end
$var wire 5 ! write_reg [4:0] $end
$var wire 32 " write_data_reg [31:0] $end
$var wire 32 # read_data [31:0] $end
$var wire 1 $ Zero $end
$var wire 32 % ReadData2 [31:0] $end
$var wire 32 & ReadData1 [31:0] $end
$var wire 32 ' PCNext [31:0] $end
$var wire 32 ( PCIn [31:0] $end
$var wire 32 ) Instruction [31:0] $end
$var wire 4 * ALUControl [3:0] $end
$var reg 1 + CLK $end
$var reg 1 , rst $end
$var integer 32 - i [31:0] $end
$scope module mcpu $end
$var wire 1 + CLK $end
$var wire 1 . bne_Zero_and $end
$var wire 1 / branch_Zero_and $end
$var wire 1 0 branching $end
$var wire 1 , rst $end
$var wire 5 1 write_reg [4:0] $end
$var wire 32 2 write_data_reg [31:0] $end
$var wire 32 3 shift_out [31:0] $end
$var wire 1 4 reg_write $end
$var wire 1 5 reg_dst $end
$var wire 32 6 read_data [31:0] $end
$var wire 32 7 pc_out_alu [31:0] $end
$var wire 1 8 mem_write $end
$var wire 1 9 mem_toreg $end
$var wire 1 : mem_read $end
$var wire 1 ; j $end
$var wire 32 < extend32 [31:0] $end
$var wire 1 = branch_ne $end
$var wire 1 > branch $end
$var wire 1 ? alu_src $end
$var wire 32 @ alu_out [31:0] $end
$var wire 4 A alu_op [3:0] $end
$var wire 32 B alu_b [31:0] $end
$var wire 32 C add_alu_out [31:0] $end
$var wire 1 $ Zero $end
$var wire 32 D ReadData2 [31:0] $end
$var wire 32 E ReadData1 [31:0] $end
$var wire 32 F PCNext [31:0] $end
$var wire 32 G PCIn [31:0] $end
$var wire 32 H Instruction [31:0] $end
$var wire 4 I ALUControl [3:0] $end
$scope module ADDRESS $end
$var wire 1 $ Zero $end
$var wire 32 J B [31:0] $end
$var wire 4 K ALUControl [3:0] $end
$var wire 32 L A [31:0] $end
$var reg 32 M alu_out [31:0] $end
$upscope $end
$scope module ADD_ALU_B $end
$var wire 32 N ShiftIn [31:0] $end
$var reg 32 O shift_out [31:0] $end
$upscope $end
$scope module AFT_RF $end
$var wire 32 P extend32 [31:0] $end
$var wire 1 ? alu_src $end
$var wire 32 Q ReadData2 [31:0] $end
$var reg 32 R alu_b [31:0] $end
$upscope $end
$scope module ALUCTRL $end
$var wire 6 S ADD [5:0] $end
$var wire 6 T AND [5:0] $end
$var wire 6 U OR [5:0] $end
$var wire 6 V SUB [5:0] $end
$var wire 6 W func [5:0] $end
$var wire 4 X alu_op [3:0] $end
$var reg 4 Y ALUControl [3:0] $end
$upscope $end
$scope module BEF_RF $end
$var wire 5 Z rd [15:11] $end
$var wire 5 [ rt [20:16] $end
$var wire 1 5 reg_dst $end
$var reg 5 \ write_reg [4:0] $end
$upscope $end
$scope module CONTROL $end
$var wire 6 ] ADDI [5:0] $end
$var wire 6 ^ ANDI [5:0] $end
$var wire 6 _ BEQ [5:0] $end
$var wire 6 ` J [5:0] $end
$var wire 6 a LW [5:0] $end
$var wire 6 b ORI [5:0] $end
$var wire 6 c RTYPE [5:0] $end
$var wire 6 d SUBI [5:0] $end
$var wire 6 e SW [5:0] $end
$var wire 6 f opcode [5:0] $end
$var reg 4 g alu_op [3:0] $end
$var reg 1 ? alu_src $end
$var reg 1 > branch $end
$var reg 1 = branch_ne $end
$var reg 1 ; j $end
$var reg 1 : mem_read $end
$var reg 1 9 mem_toreg $end
$var reg 1 8 mem_write $end
$var reg 1 5 reg_dst $end
$var reg 1 4 reg_write $end
$upscope $end
$scope module DM $end
$var wire 1 + CLK $end
$var wire 32 h addr [31:0] $end
$var wire 1 : mem_read $end
$var wire 1 8 mem_write $end
$var wire 32 i write_data [31:0] $end
$var reg 32 j read_data [31:0] $end
$var integer 32 k i [31:0] $end
$upscope $end
$scope module IM $end
$var wire 1 + CLK $end
$var wire 32 l address [31:0] $end
$var reg 32 m Instruction [31:0] $end
$upscope $end
$scope module JUPM $end
$var wire 1 ; j $end
$var wire 32 n pc_out_alu [31:0] $end
$var wire 32 o ReadData1 [31:0] $end
$var reg 32 p PCIn [31:0] $end
$upscope $end
$scope module PC $end
$var wire 1 + CLK $end
$var wire 32 q PCIn [31:0] $end
$var wire 1 , rst $end
$var reg 32 r PCNext [31:0] $end
$upscope $end
$scope module PCADDER $end
$var wire 32 s PCNext [31:0] $end
$var wire 32 t shift_out [31:0] $end
$var reg 32 u add_alu_out [31:0] $end
$upscope $end
$scope module RF $end
$var wire 1 + CLK $end
$var wire 32 v ReadData1 [31:0] $end
$var wire 32 w ReadData2 [31:0] $end
$var wire 5 x read_reg1 [4:0] $end
$var wire 5 y read_reg2 [4:0] $end
$var wire 1 4 reg_write $end
$var wire 5 z write_reg [4:0] $end
$var wire 32 { write_data [31:0] $end
$upscope $end
$scope module SE16TO32 $end
$var wire 16 | in16 [15:0] $end
$var reg 32 } out32 [31:0] $end
$upscope $end
$scope module mu3_0 $end
$var wire 32 ~ alu_out [31:0] $end
$var wire 1 9 mem_toreg $end
$var wire 32 !" read_data [31:0] $end
$var reg 32 "" write_data_reg [31:0] $end
$upscope $end
$scope module mux4_0 $end
$var wire 32 #" PCNext [31:0] $end
$var wire 32 $" add_alu_out [31:0] $end
$var wire 1 0 branch_Zero_and $end
$var reg 32 %" PCIn [31:0] $end
$upscope $end
$upscope $end
$upscope $end
$enddefinitions $end
#0
$dumpvars
b0 %"
bx $"
b0 #"
bx ""
b0 !"
bx ~
bx }
bx |
bx {
bx z
bx y
bx x
bx w
bx v
bx u
bx t
b0 s
b0 r
b0 q
b0 p
bx o
b0 n
bx m
b0 l
b100000000 k
b0 j
bx i
bx h
bx g
bx f
b101011 e
b100111 d
b0 c
b110010 b
b100011 a
b10 `
b100 _
b101111 ^
b1000 ]
bx \
bx [
bx Z
bx Y
bx X
bx W
b100010 V
b100101 U
b100100 T
b100000 S
bx R
bx Q
bx P
bx O
bx N
bx M
bx L
bx K
bx J
bx I
bx H
b0 G
b0 F
bx E
bx D
bx C
bx B
bx A
bx @
0?
0>
x=
bx <
0;
0:
09
08
b0 7
b0 6
05
04
bx 3
bx 2
bx 1
x0
0/
x.
bx -
1,
1+
bx *
bx )
b0 (
b0 '
bx &
bx %
x$
b0 #
bx "
bx !
$end
#50
0+
b0 -
0,
#100
b100 (
b100 G
b100 l
b100 p
b100 q
b100 7
b100 n
b100 %"
b100 '
b100 F
b100 r
b100 s
b100 #"
1+
b1 -
#150
0+
b10 -
#200
b1000000010001000 C
b1000000010001000 u
b1000000010001000 $"
b1000 (
b1000 G
b1000 l
b1000 p
b1000 q
b1000000010000000 3
b1000000010000000 O
b1000000010000000 t
b10100 "
b10100 2
b10100 {
b10100 ""
b10000000100000 <
b10000000100000 N
b10000000100000 P
b10000000100000 }
b100 !
b100 1
b100 \
b100 z
b10 *
b10 I
b10 K
b10 Y
b1111 A
b1111 X
b1111 g
14
15
b100 B
b100 J
b100 R
b1000 7
b1000 n
b1000 %"
x0
x.
0$
b10100 @
b10100 M
b10100 h
b10100 ~
b10000000100000 |
b100 Z
b1 [
b100000 W
b0 f
b100 %
b100 D
b100 Q
b100 i
b100 w
b1 y
b10000 &
b10000 E
b10000 L
b10000 o
b10000 v
b100 x
b1000 '
b1000 F
b1000 r
b1000 s
b1000 #"
b100000010010000000100000 )
b100000010010000000100000 H
b100000010010000000100000 m
1+
b11 -
#250
0+
b100 -
#300
b1100 (
b1100 G
b1100 l
b1100 p
b1100 q
b1100 3
b1100 O
b1100 t
b11 <
b11 N
b11 P
b11 }
b101 !
b101 1
b101 \
b101 z
b0 A
b0 X
b0 g
18
1:
1?
14
05
b11 B
b11 J
b11 R
b11000 C
b11000 u
b11000 $"
b1100 7
b1100 n
b1100 %"
b11 |
b0 Z
b101 [
b11 W
b100011 f
b10000 %
b10000 D
b10000 Q
b10000 i
b10000 w
b101 y
b1 x
b111 "
b111 2
b111 {
b111 ""
b10001100001001010000000000000011 )
b10001100001001010000000000000011 H
b10001100001001010000000000000011 m
b1100 '
b1100 F
b1100 r
b1100 s
b1100 #"
b111 @
b111 M
b111 h
b111 ~
b100 &
b100 E
b100 L
b100 o
b100 v
1+
b101 -
#350
0+
b110 -
#400
b1100 B
b1100 J
b1100 R
b10000 (
b10000 G
b10000 l
b10000 p
b10000 q
b1000000010101100 3
b1000000010101100 O
b1000000010101100 t
b10011 "
b10011 2
b10011 {
b10011 ""
b10000000101011 <
b10000000101011 N
b10000000101011 P
b10000000101011 }
b100 !
b100 1
b100 \
b100 z
b1111 A
b1111 X
b1111 g
15
08
0:
14
0?
b1000000010111100 C
b1000000010111100 u
b1000000010111100 $"
b10000 7
b10000 n
b10000 %"
b10011 @
b10011 M
b10011 h
b10011 ~
b10000000101011 |
b100 Z
b11 [
b101011 W
b0 f
b11 y
b111 &
b111 E
b111 L
b111 o
b111 v
b101 x
b10000 '
b10000 F
b10000 r
b10000 s
b10000 #"
b101000110010000000101011 )
b101000110010000000101011 H
b101000110010000000101011 m
b111 #
b111 6
b111 j
b111 !"
b1100 %
b1100 D
b1100 Q
b1100 i
b1100 w
1+
b111 -
#450
0+
b1000 -
#500
0.
10
1/
1$
b11 *
b11 I
b11 K
b11 Y
b110000 (
b110000 G
b110000 l
b110000 p
b110000 q
b11100 3
b11100 O
b11100 t
b0 "
b0 2
b0 {
b0 ""
b111 <
b111 N
b111 P
b111 }
b111 !
b111 1
b111 \
b111 z
b1 A
b1 X
b1 g
1>
04
05
b10000 B
b10000 J
b10000 R
b110000 C
b110000 u
b110000 $"
b110000 7
b110000 n
b110000 %"
b0 @
b0 M
b0 h
b0 ~
b111 |
b0 Z
b111 [
b111 W
b100 f
b10000 %
b10000 D
b10000 Q
b10000 i
b10000 w
b111 y
b10000 &
b10000 E
b10000 L
b10000 o
b10000 v
b111 x
b10000111001110000000000000111 )
b10000111001110000000000000111 H
b10000111001110000000000000111 m
b10100 '
b10100 F
b10100 r
b10100 s
b10100 #"
1+
b1001 -
#550
0+
b1010 -
#600
b110100 (
b110100 G
b110100 l
b110100 p
b110100 q
b0xxxxxxxxxxxxxxxx00 3
b0xxxxxxxxxxxxxxxx00 O
b0xxxxxxxxxxxxxxxx00 t
b110100 7
b110100 n
b110100 %"
bx "
bx 2
bx {
bx ""
b0xxxxxxxxxxxxxxxx <
b0xxxxxxxxxxxxxxxx N
b0xxxxxxxxxxxxxxxx P
b0xxxxxxxxxxxxxxxx }
bx !
bx 1
bx \
bx z
0>
bx B
bx J
bx R
bx C
bx u
bx $"
x.
x0
0/
x$
bx @
bx M
bx h
bx ~
bx |
bx Z
bx [
bx W
bx f
bx %
bx D
bx Q
bx i
bx w
bx y
bx &
bx E
bx L
bx o
bx v
bx x
b110100 '
b110100 F
b110100 r
b110100 s
b110100 #"
bx )
bx H
bx m
1+
b1011 -
#650
0+
b1100 -
#700
b111000 (
b111000 G
b111000 l
b111000 p
b111000 q
b111000 7
b111000 n
b111000 %"
b111000 '
b111000 F
b111000 r
b111000 s
b111000 #"
1+
b1101 -
#750
0+
b1110 -
#800
b111100 (
b111100 G
b111100 l
b111100 p
b111100 q
b111100 7
b111100 n
b111100 %"
b111100 '
b111100 F
b111100 r
b111100 s
b111100 #"
1+
b1111 -
#850
0+
b10000 -
#900
b1000000 (
b1000000 G
b1000000 l
b1000000 p
b1000000 q
b1000000 7
b1000000 n
b1000000 %"
b1000000 '
b1000000 F
b1000000 r
b1000000 s
b1000000 #"
1+
b10001 -
#950
0+
b10010 -
#1000
b1000100 (
b1000100 G
b1000100 l
b1000100 p
b1000100 q
b1000100 7
b1000100 n
b1000100 %"
b1000100 '
b1000100 F
b1000100 r
b1000100 s
b1000100 #"
1+
b10011 -
#1050
b10100 -
